Pokeno/__init__.py
Pokeno/random_pokemon.py
Pokeno-1.0.1.dist-info/METADATA
Pokeno-1.0.1.dist-info/WHEEL
Pokeno-1.0.1.dist-info/top_level.txt
Pokeno-1.0.1.dist-info/RECORD
